setup.py
uci_5640/__init__.py
uci_5640/news.py
uci_5640.egg-info/PKG-INFO
uci_5640.egg-info/SOURCES.txt
uci_5640.egg-info/dependency_links.txt
uci_5640.egg-info/requires.txt
uci_5640.egg-info/top_level.txt