Metadata-Version: 2.1
Name: uci-5640
Version: 0.1.7
Summary: For fun
Author: Xuhu Wan
Author-email: xuhu.wan@gmail.com
